README.rst
setup.py
venn/__init__.py
venn/exceptions.py
venn/places_api.py
venn_places.egg-info/PKG-INFO
venn_places.egg-info/SOURCES.txt
venn_places.egg-info/dependency_links.txt
venn_places.egg-info/requires.txt
venn_places.egg-info/top_level.txt