Metadata-Version: 1.1
Name: venn-places
Version: 0.0.1
Summary: Get normalized place data from Foursquare, Yelp, Facebook, Google, and Factual.
Home-page: http://github.com/vennhq/venn-places-python
Author: Bryon Meinka
Author-email: b.meinka@gmail.com
License: UNKNOWN
Platform: UNKNOWN
Classifier: Intended Audience :: Developers
Classifier: Natural Language :: English
Classifier: Programming Language :: Python
Classifier: Programming Language :: Python :: 2.7
Classifier: Programming Language :: Python :: 3
